translation_engines/__init__.py
translation_engines/engines.py
translation_engines/engines_private.py
harken_translation_engines-0.1.3.dist-info/METADATA
harken_translation_engines-0.1.3.dist-info/WHEEL
harken_translation_engines-0.1.3.dist-info/RECORD
